{"card_name": "Sage of Aenir's Reclamation", "color": "U", "rarity": "uncommon", "type": "Creature \u2013 Human Wizard Ally", "number": 51, "color_identity": "URG", "cost": "{1}{U}", "rules_text": "Attune [i](Add text based on basic land types among different lands you control)[/i]\nOnce each turn, when you conjure a card,\n{G}{G}|Search your library for a basic land card, put it into your hand, then shuffle.\n{R}{R}|You may discard a card. If you do, draw a card.", "pt": "1/3", "special_text": "", "shape": "normal", "set": "SHS", "loyalty": "", "notes": ""}