{"card_name": "Wielder of Stars", "color": "U", "rarity": "rare", "type": "Creature \u2013 Human Warlock", "number": 57, "color_identity": "U", "cost": "{9}{U}", "rules_text": "As an additional cost to cast this spell, discard up to three cards. This spell costs {2} less to cast for each card discarded this way.\nWhen Wielder of Stars enters or attacks, acquire an instant or sorcery card.  [i](Reveal cards from the top of your library until you reveal an instant or sorcery card. Put that card into your hand and the rest on the bottom of your library in a random order.)[/i]", "pt": "2/5", "special_text": "", "shape": "normal", "set": "SHS", "loyalty": "", "notes": ""}